{
  "id": "6aa210cb-4722-40a1-96ea-f8f36a906def",
  "prevId": "c32f78e4-31e4-4dc7-838f-97e3d808507b",
  "version": "7",
  "dialect": "postgresql",
  "tables": {
    "public.progress": {
      "name": "progress",
      "schema": "",
      "columns": {
        "id": {
          "name": "id",
          "type": "serial",
          "primaryKey": true,
          "notNull": true
        },
        "user_id": {
          "name": "user_id",
          "type": "text",
          "primaryKey": false,
          "notNull": true
        },
        "topic_id": {
          "name": "topic_id",
          "type": "integer",
          "primaryKey": false,
          "notNull": true
        },
        "task_id": {
          "name": "task_id",
          "type": "integer",
          "primaryKey": false,
          "notNull": false
        },
        "completed": {
          "name": "completed",
          "type": "boolean",
          "primaryKey": false,
          "notNull": true,
          "default": false
        },
        "score": {
          "name": "score",
          "type": "integer",
          "primaryKey": false,
          "notNull": false
        },
        "answered_at": {
          "name": "answered_at",
          "type": "timestamp",
          "primaryKey": false,
          "notNull": false,
          "default": "now()"
        }
      },
      "indexes": {},
      "foreignKeys": {
        "progress_user_id_users_id_fk": {
          "name": "progress_user_id_users_id_fk",
          "tableFrom": "progress",
          "tableTo": "users",
          "columnsFrom": [
            "user_id"
          ],
          "columnsTo": [
            "id"
          ],
          "onDelete": "cascade",
          "onUpdate": "no action"
        },
        "progress_topic_id_topics_id_fk": {
          "name": "progress_topic_id_topics_id_fk",
          "tableFrom": "progress",
          "tableTo": "topics",
          "columnsFrom": [
            "topic_id"
          ],
          "columnsTo": [
            "id"
          ],
          "onDelete": "cascade",
          "onUpdate": "no action"
        },
        "progress_task_id_tasks_id_fk": {
          "name": "progress_task_id_tasks_id_fk",
          "tableFrom": "progress",
          "tableTo": "tasks",
          "columnsFrom": [
            "task_id"
          ],
          "columnsTo": [
            "id"
          ],
          "onDelete": "set null",
          "onUpdate": "no action"
        }
      },
      "compositePrimaryKeys": {},
      "uniqueConstraints": {},
      "policies": {},
      "checkConstraints": {},
      "isRLSEnabled": false
    },
    "public.roads": {
      "name": "roads",
      "schema": "",
      "columns": {
        "id": {
          "name": "id",
          "type": "serial",
          "primaryKey": true,
          "notNull": true
        },
        "title": {
          "name": "title",
          "type": "text",
          "primaryKey": false,
          "notNull": true
        },
        "description": {
          "name": "description",
          "type": "text",
          "primaryKey": false,
          "notNull": true
        },
        "user_id": {
          "name": "user_id",
          "type": "text",
          "primaryKey": false,
          "notNull": true
        },
        "created_at": {
          "name": "created_at",
          "type": "timestamp",
          "primaryKey": false,
          "notNull": true,
          "default": "now()"
        }
      },
      "indexes": {},
      "foreignKeys": {
        "roads_user_id_users_id_fk": {
          "name": "roads_user_id_users_id_fk",
          "tableFrom": "roads",
          "tableTo": "users",
          "columnsFrom": [
            "user_id"
          ],
          "columnsTo": [
            "id"
          ],
          "onDelete": "cascade",
          "onUpdate": "no action"
        }
      },
      "compositePrimaryKeys": {},
      "uniqueConstraints": {},
      "policies": {},
      "checkConstraints": {},
      "isRLSEnabled": false
    },
    "public.support_prompts": {
      "name": "support_prompts",
      "schema": "",
      "columns": {
        "id": {
          "name": "id",
          "type": "serial",
          "primaryKey": true,
          "notNull": true
        },
        "topic_id": {
          "name": "topic_id",
          "type": "integer",
          "primaryKey": false,
          "notNull": true
        },
        "question": {
          "name": "question",
          "type": "text",
          "primaryKey": false,
          "notNull": true
        },
        "order": {
          "name": "order",
          "type": "integer",
          "primaryKey": false,
          "notNull": false
        }
      },
      "indexes": {},
      "foreignKeys": {
        "support_prompts_topic_id_topics_id_fk": {
          "name": "support_prompts_topic_id_topics_id_fk",
          "tableFrom": "support_prompts",
          "tableTo": "topics",
          "columnsFrom": [
            "topic_id"
          ],
          "columnsTo": [
            "id"
          ],
          "onDelete": "cascade",
          "onUpdate": "no action"
        }
      },
      "compositePrimaryKeys": {},
      "uniqueConstraints": {},
      "policies": {},
      "checkConstraints": {},
      "isRLSEnabled": false
    },
    "public.tasks": {
      "name": "tasks",
      "schema": "",
      "columns": {
        "id": {
          "name": "id",
          "type": "serial",
          "primaryKey": true,
          "notNull": true
        },
        "topic_id": {
          "name": "topic_id",
          "type": "integer",
          "primaryKey": false,
          "notNull": true
        },
        "question": {
          "name": "question",
          "type": "text",
          "primaryKey": false,
          "notNull": true
        },
        "answer": {
          "name": "answer",
          "type": "text",
          "primaryKey": false,
          "notNull": true
        },
        "type": {
          "name": "type",
          "type": "text",
          "primaryKey": false,
          "notNull": true
        },
        "order": {
          "name": "order",
          "type": "integer",
          "primaryKey": false,
          "notNull": false
        },
        "created_at": {
          "name": "created_at",
          "type": "timestamp",
          "primaryKey": false,
          "notNull": true,
          "default": "now()"
        }
      },
      "indexes": {},
      "foreignKeys": {
        "tasks_topic_id_topics_id_fk": {
          "name": "tasks_topic_id_topics_id_fk",
          "tableFrom": "tasks",
          "tableTo": "topics",
          "columnsFrom": [
            "topic_id"
          ],
          "columnsTo": [
            "id"
          ],
          "onDelete": "cascade",
          "onUpdate": "no action"
        }
      },
      "compositePrimaryKeys": {},
      "uniqueConstraints": {},
      "policies": {},
      "checkConstraints": {},
      "isRLSEnabled": false
    },
    "public.topics": {
      "name": "topics",
      "schema": "",
      "columns": {
        "id": {
          "name": "id",
          "type": "serial",
          "primaryKey": true,
          "notNull": true
        },
        "road_id": {
          "name": "road_id",
          "type": "integer",
          "primaryKey": false,
          "notNull": true
        },
        "title": {
          "name": "title",
          "type": "text",
          "primaryKey": false,
          "notNull": true
        },
        "description": {
          "name": "description",
          "type": "text",
          "primaryKey": false,
          "notNull": false
        },
        "created_by_ai": {
          "name": "created_by_ai",
          "type": "boolean",
          "primaryKey": false,
          "notNull": false,
          "default": true
        },
        "created_at": {
          "name": "created_at",
          "type": "timestamp",
          "primaryKey": false,
          "notNull": true,
          "default": "now()"
        }
      },
      "indexes": {},
      "foreignKeys": {
        "topics_road_id_roads_id_fk": {
          "name": "topics_road_id_roads_id_fk",
          "tableFrom": "topics",
          "tableTo": "roads",
          "columnsFrom": [
            "road_id"
          ],
          "columnsTo": [
            "id"
          ],
          "onDelete": "cascade",
          "onUpdate": "no action"
        }
      },
      "compositePrimaryKeys": {},
      "uniqueConstraints": {},
      "policies": {},
      "checkConstraints": {},
      "isRLSEnabled": false
    },
    "public.users": {
      "name": "users",
      "schema": "",
      "columns": {
        "id": {
          "name": "id",
          "type": "text",
          "primaryKey": true,
          "notNull": true
        },
        "name": {
          "name": "name",
          "type": "text",
          "primaryKey": false,
          "notNull": true
        },
        "email": {
          "name": "email",
          "type": "text",
          "primaryKey": false,
          "notNull": true
        },
        "trial": {
          "name": "trial",
          "type": "text",
          "primaryKey": false,
          "notNull": false,
          "default": "'free'"
        },
        "credits": {
          "name": "credits",
          "type": "integer",
          "primaryKey": false,
          "notNull": true,
          "default": 1
        },
        "created_at": {
          "name": "created_at",
          "type": "timestamp",
          "primaryKey": false,
          "notNull": true,
          "default": "now()"
        }
      },
      "indexes": {},
      "foreignKeys": {},
      "compositePrimaryKeys": {},
      "uniqueConstraints": {
        "users_email_unique": {
          "name": "users_email_unique",
          "nullsNotDistinct": false,
          "columns": [
            "email"
          ]
        }
      },
      "policies": {},
      "checkConstraints": {},
      "isRLSEnabled": false
    }
  },
  "enums": {},
  "schemas": {},
  "sequences": {},
  "roles": {},
  "policies": {},
  "views": {},
  "_meta": {
    "columns": {},
    "schemas": {},
    "tables": {}
  }
}